{
    "name": "ExampleSubmission",
    "fields": [
        {
            "fieldName": "usedForTutorial",
            "fieldType": "Boolean"
        }
    ],
    "relationships": [
        {
            "relationshipType": "one-to-one",
            "otherEntityName": "submission",
            "otherEntityRelationshipName": "exampleSubmission",
            "relationshipName": "submission",
            "otherEntityField": "id",
            "ownerSide": true
        },
        {
            "relationshipType": "many-to-one",
            "otherEntityName": "exercise",
            "otherEntityRelationshipName": "exampleSubmissions",
            "relationshipName": "exercise",
            "otherEntityField": "id"
        },
        {
            "relationshipName": "tutorParticipation",
            "otherEntityName": "tutorParticipation",
            "relationshipType": "many-to-one",
            "otherEntityField": "id"
        }
    ],
    "changelogDate": "20190315161939",
    "entityTableName": "example_submission",
    "dto": "no",
    "pagination": "no",
    "service": "no",
    "jpaMetamodelFiltering": false,
    "fluentMethods": true,
    "clientRootFolder": "",
    "applications": "*"
}