<?xml version="1.0" encoding="utf-8"?>
<databaseChangeLog
    xmlns="http://www.liquibase.org/xml/ns/dbchangelog"
    xmlns:xsi="http://www.w3.org/2001/XMLSchema-instance"
    xsi:schemaLocation="http://www.liquibase.org/xml/ns/dbchangelog http://www.liquibase.org/xml/ns/dbchangelog/dbchangelog-4.3.xsd">

    <changeSet id="20260515120000-1" author="KilianSen">
        <preConditions onFail="MARK_RAN">
            <not><columnExists tableName="proof_exercise_details" columnName="partial_credit_enabled"/></not>
        </preConditions>
        <addColumn tableName="proof_exercise_details">
            <column name="partial_credit_enabled" type="boolean" defaultValueBoolean="false">
                <constraints nullable="false"/>
            </column>
        </addColumn>
    </changeSet>

</databaseChangeLog>
